{
  "Jan": [
    {
      "Condition": "Partially cloudy",
      "Temperature_Min": " -7.6",
      "Temperature_Max": " 13.3",
      "Dew_Min": "-5.9",
      "Dew_Max": "10.2",
      "Feelslike_Min": "-6",
      "Feelslike_Max": "10.8",
      "Snow_Min": "0",
      "Snow_Max": "0",
      "Humidity_Min": "61.3",
      "Humidity_Max": "94.6",
      "Precip_Min": "1",
      "Precip_Max": "18.957",
      "PrecipProb_Min": "0",
      "PrecipProb_Max": "100",
      "Pressure_Min": "1000.5",
      "Pressure_Max": "1036.8",
      "UVIndex_Min": "1",
      "UVIndex_Max": " 4",
      "Visibility_Min": " 8.2",
      "Visibility_Max": "16",
      "WindSpeed_Min": "7",
      "WindSpeed_Max": "31",
      "WindDirection_Min": "6.1",
      "WindDirection_Max": "359.2",
      "Sunrise_Max": " 07:36:58",
      "Sunrise_Min": "07:57:39",
      "Sunset_Max": "16:28:39",
      "Sunset_Min": "17:09:17",
      "Moonrise_Max": "00:42:31",
      "Moonrise_Min": "22:13:46",
      "Moonset_Max": "01:08:42",
      "Moonset_Min": "17:36:36"
    },
    {
      "Condition": "Rain",
      "Temperature_Min": " -1.1",
      "Temperature_Max": " 13.3",
      "Dew_Min": "-1.3",
      "Dew_Max": "10.2",
      "Feelslike_Min": "-1.3",
      "Feelslike_Max": "10.8",
      "Snow_Min": "0",
      "Snow_Max": "0",
      "Humidity_Min": "76",
      "Humidity_Max": "95.2",
      "Precip_Min": "0.047",
      "Precip_Max": "25.292",
      "PrecipProb_Min": "100",
      "PrecipProb_Max": "100",
      "Pressure_Min": "1000.3",
      "Pressure_Max": "1027",
      "UVIndex_Min": "0",
      "UVIndex_Max": " 3",
      "Visibility_Min": " 8",
      "Visibility_Max": "15.1",
      "WindSpeed_Min": "10.7",
      "WindSpeed_Max": "31",
      "WindDirection_Min": "40.6",
      "WindDirection_Max": "191.1",
      "Sunrise_Max": " 07:38:13",
      "Sunrise_Min": "07:57:37",
      "Sunset_Max": "16:29:38",
      "Sunset_Min": "17:07:43",
      "Moonrise_Max": "07:02:33",
      "Moonrise_Min": "19:50:59",
      "Moonset_Max": "01:08:42",
      "Moonset_Min": "22:50:35"
    },
    {
      "Condition": "Snow",
      "Temperature_Min": " 0.9",
      "Temperature_Max": " 4.8",
      "Dew_Min": "0.9",
      "Dew_Max": "1.6",
      "Feelslike_Min": "-1.3",
      "Feelslike_Max": "2",
      "Snow_Min": "0",
      "Snow_Max": "0",
      "Humidity_Min": "90",
      "Humidity_Max": "90.4",
      "Precip_Min": "1.914",
      "Precip_Max": "16.461",
      "PrecipProb_Min": "100",
      "PrecipProb_Max": "100",
      "Pressure_Min": "1000.5",
      "Pressure_Max": "1020",
      "UVIndex_Min": "1",
      "UVIndex_Max": " 2",
      "Visibility_Min": " 12.8",
      "Visibility_Max": "14",
      "WindSpeed_Min": "10.7",
      "WindSpeed_Max": "23.2",
      "WindDirection_Min": "40.6",
      "WindDirection_Max": "162.4",
      "Sunrise_Max": " 07:57:11",
      "Sunrise_Min": "07:57:31",
      "Sunset_Max": "16:30:40",
      "Sunset_Min": "16:32:49",
      "Moonrise_Max": "09:18:40",
      "Moonrise_Min": "10:32:08",
      "Moonset_Max": "17:36:36",
      "Moonset_Min": "20:19:54"
    },
    {
      "Condition": "Cloudy",
      "Temperature_Min": " 1.5",
      "Temperature_Max": " 11.5",
      "Dew_Min": "1.6",
      "Dew_Max": "9",
      "Feelslike_Min": "0.4",
      "Feelslike_Max": "9.2",
      "Snow_Min": "0",
      "Snow_Max": "0",
      "Humidity_Min": "83.2",
      "Humidity_Max": "97.7",
      "Precip_Min": "2",
      "Precip_Max": "25.292",
      "PrecipProb_Min": "0",
      "PrecipProb_Max": "100",
      "Pressure_Min": "1000.3",
      "Pressure_Max": "1029.3",
      "UVIndex_Min": "0",
      "UVIndex_Max": " 3",
      "Visibility_Min": " 2.6",
      "Visibility_Max": "14.9",
      "WindSpeed_Min": "9.1",
      "WindSpeed_Max": "30.8",
      "WindDirection_Min": "1.8",
      "WindDirection_Max": "191.1",
      "Sunrise_Max": " 07:45:04",
      "Sunrise_Min": "07:57:23",
      "Sunset_Max": "16:31:44",
      "Sunset_Min": "16:58:27",
      "Moonrise_Max": "10:00:52",
      "Moonrise_Min": "23:27:21",
      "Moonset_Max": "02:15:30",
      "Moonset_Min": "22:50:35"
    },
    {
      "Condition": "Sunny",
      "Temperature_Min": " -1.8",
      "Temperature_Max": " 10.8",
      "Dew_Min": "-2.1",
      "Dew_Max": "1",
      "Feelslike_Min": "2.2",
      "Feelslike_Max": "3.7",
      "Snow_Min": "0",
      "Snow_Max": "0",
      "Humidity_Min": "71.9",
      "Humidity_Max": "83.3",
      "Precip_Min": "0",
      "Precip_Max": "0",
      "PrecipProb_Min": "0",
      "PrecipProb_Max": "0",
      "Pressure_Min": "1026",
      "Pressure_Max": "1026.9",
      "UVIndex_Min": "3",
      "UVIndex_Max": " 3",
      "Visibility_Min": " 12.5",
      "Visibility_Max": "15.6",
      "WindSpeed_Min": "7",
      "WindSpeed_Max": "12.9",
      "WindDirection_Min": "12.8",
      "WindDirection_Max": "153.8",
      "Sunrise_Max": " 07:40:38",
      "Sunrise_Min": "07:55:58",
      "Sunset_Max": "16:37:31",
      "Sunset_Min": "17:04:36",
      "Moonrise_Max": "04:43:53",
      "Moonrise_Min": "11:51:35",
      "Moonset_Max": "00:00:37",
      "Moonset_Min": "12:58:21"
    }
  ],
  "Feb": [
    {
      "Condition": "Cloudy",
      "Temperature_Min": " -2.5",
      "Temperature_Max": " 12.9",
      "Dew_Min": "-6.6",
      "Dew_Max": "10.1",
      "Feelslike_Min": "-3.7",
      "Feelslike_Max": "10",
      "Snow_Min": "0",
      "Snow_Max": "0.3",
      "Humidity_Min": "61.5",
      "Humidity_Max": "95.1",
      "Precip_Min": "2",
      "Precip_Max": "38.976",
      "PrecipProb_Min": "0",
      "PrecipProb_Max": "100",
      "Pressure_Min": "1012.7",
      "Pressure_Max": "1036.5",
      "UVIndex_Min": "1",
      "UVIndex_Max": " 4",
      "Visibility_Min": " 7.8",
      "Visibility_Max": "15.9",
      "WindSpeed_Min": "10.9",
      "WindSpeed_Max": "30.1",
      "WindDirection_Min": "7.7",
      "WindDirection_Max": "342.1",
      "Sunrise_Max": " 06:51:22",
      "Sunrise_Min": "07:35:40",
      "Sunset_Max": "17:10:51",
      "Sunset_Min": "17:53:00",
      "Moonrise_Max": "05:44:47",
      "Moonrise_Min": "22:33:01",
      "Moonset_Max": "01:09:56",
      "Moonset_Min": "21:42:00"
    },
    {
      "Condition": "Partially cloudy",
      "Temperature_Min": " -5.2",
      "Temperature_Max": " 11.9",
      "Dew_Min": "-11.9",
      "Dew_Max": "5.4",
      "Feelslike_Min": "-2.4",
      "Feelslike_Max": "8.5",
      "Snow_Min": "0",
      "Snow_Max": "0.2",
      "Humidity_Min": "43.6",
      "Humidity_Max": "88.5",
      "Precip_Min": "1",
      "Precip_Max": "6.382",
      "PrecipProb_Min": "0",
      "PrecipProb_Max": "100",
      "Pressure_Min": "1013",
      "Pressure_Max": "1035.9",
      "UVIndex_Min": "1",
      "UVIndex_Max": " 6",
      "Visibility_Min": " 10.5",
      "Visibility_Max": "16",
      "WindSpeed_Min": "8",
      "WindSpeed_Max": "22.9",
      "WindDirection_Min": "3.4",
      "WindDirection_Max": "359",
      "Sunrise_Max": " 06:55:07",
      "Sunrise_Min": "07:34:21",
      "Sunset_Max": "17:12:25",
      "Sunset_Min": "17:49:58",
      "Moonrise_Max": "01:10:42",
      "Moonrise_Min": "23:51:01",
      "Moonset_Max": "00:01:37",
      "Moonset_Min": "22:52:27"
    },
    {
      "Condition": "Rain",
      "Temperature_Min": " -0.3",
      "Temperature_Max": " 12.9",
      "Dew_Min": "-2.8",
      "Dew_Max": "10.1",
      "Feelslike_Min": "0.6",
      "Feelslike_Max": "10",
      "Snow_Min": "0",
      "Snow_Max": "0",
      "Humidity_Min": "62.2",
      "Humidity_Max": "95.1",
      "Precip_Min": "0.025",
      "Precip_Max": "38.976",
      "PrecipProb_Min": "100",
      "PrecipProb_Max": "100",
      "Pressure_Min": "1012.7",
      "Pressure_Max": "1035.4",
      "UVIndex_Min": "1",
      "UVIndex_Max": " 5",
      "Visibility_Min": " 7.8",
      "Visibility_Max": "15.5",
      "WindSpeed_Min": "14.8",
      "WindSpeed_Max": "30.1",
      "WindDirection_Min": "146",
      "WindDirection_Max": "359",
      "Sunrise_Max": " 06:51:22",
      "Sunrise_Min": "07:33:00",
      "Sunset_Max": "17:14:00",
      "Sunset_Min": "17:53:00",
      "Moonrise_Max": "04:51:52",
      "Moonrise_Min": "23:51:01",
      "Moonset_Max": "06:48:21",
      "Moonset_Min": "22:52:27"
    },
    {
      "Condition": "Sunny",
      "Temperature_Min": " -3.6",
      "Temperature_Max": " 13.9",
      "Dew_Min": "-4",
      "Dew_Max": "2.5",
      "Feelslike_Min": "1",
      "Feelslike_Max": "5.5",
      "Snow_Min": "0",
      "Snow_Max": "0",
      "Humidity_Min": "67.4",
      "Humidity_Max": "75.9",
      "Precip_Min": "0",
      "Precip_Max": "0",
      "PrecipProb_Min": "0",
      "PrecipProb_Max": "0",
      "Pressure_Min": "1021.2",
      "Pressure_Max": "1029.9",
      "UVIndex_Min": "5",
      "UVIndex_Max": " 6",
      "Visibility_Min": " 14.5",
      "Visibility_Max": "15.9",
      "WindSpeed_Min": "10.9",
      "WindSpeed_Max": "16.6",
      "WindDirection_Min": "138.3",
      "WindDirection_Max": "352.6",
      "Sunrise_Max": " 06:56:59",
      "Sunrise_Min": "07:19:34",
      "Sunset_Max": "17:28:14",
      "Sunset_Min": "17:48:26",
      "Moonrise_Max": "03:46:20",
      "Moonrise_Min": "14:12:05",
      "Moonset_Max": "05:21:11",
      "Moonset_Min": "11:42:47"
    },
    {
      "Condition": "Snow",
      "Temperature_Min": " -0.3",
      "Temperature_Max": " 5.8",
      "Dew_Min": "-0.8",
      "Dew_Max": "-0.8",
      "Feelslike_Min": "0.6",
      "Feelslike_Max": "0.6",
      "Snow_Min": "0",
      "Snow_Max": "0",
      "Humidity_Min": "76.2",
      "Humidity_Max": "76.2",
      "Precip_Min": "0.43",
      "Precip_Max": "0.43",
      "PrecipProb_Min": "100",
      "PrecipProb_Max": "100",
      "Pressure_Min": "1013",
      "Pressure_Max": "1013",
      "UVIndex_Min": "5",
      "UVIndex_Max": " 5",
      "Visibility_Min": " 14.8",
      "Visibility_Max": "14.8",
      "WindSpeed_Min": "22.9",
      "WindSpeed_Max": "22.9",
      "WindDirection_Min": "359",
      "WindDirection_Max": "359",
      "Sunrise_Max": " 07:04:15",
      "Sunrise_Min": "07:04:15",
      "Sunset_Max": "17:42:18",
      "Sunset_Min": "17:42:18",
      "Moonrise_Max": "23:51:01",
      "Moonrise_Min": "23:51:01",
      "Moonset_Max": "09:23:31",
      "Moonset_Min": "09:23:31"
    }
  ],
  "Mar": [
    {
      "Condition": "Rain",
      "Temperature_Min": " 3",
      "Temperature_Max": " 18.2",
      "Dew_Min": "1.5",
      "Dew_Max": "10.2",
      "Feelslike_Min": "3.6",
      "Feelslike_Max": "12.1",
      "Snow_Min": "0",
      "Snow_Max": "0",
      "Humidity_Min": "64.4",
      "Humidity_Max": "91.8",
      "Precip_Min": "0.025",
      "Precip_Max": "8.334",
      "PrecipProb_Min": "100",
      "PrecipProb_Max": "100",
      "Pressure_Min": "1012.2",
      "Pressure_Max": "1027.3",
      "UVIndex_Min": "1",
      "UVIndex_Max": " 9",
      "Visibility_Min": " 11.8",
      "Visibility_Max": "15.9",
      "WindSpeed_Min": "11.1",
      "WindSpeed_Max": "26.2",
      "WindDirection_Min": "1.3",
      "WindDirection_Max": "353.4",
      "Sunrise_Max": " 06:27:57",
      "Sunrise_Min": "07:25:57",
      "Sunset_Max": "17:54:31",
      "Sunset_Min": "19:38:07",
      "Moonrise_Max": "01:20:57",
      "Moonrise_Min": "23:59:18",
      "Moonset_Max": "00:02:08",
      "Moonset_Min": "20:31:27"
    },
    {
      "Condition": "Partially cloudy",
      "Temperature_Min": " -1.9",
      "Temperature_Max": " 18.2",
      "Dew_Min": "-5.7",
      "Dew_Max": "10.2",
      "Feelslike_Min": "3.1",
      "Feelslike_Max": "12.1",
      "Snow_Min": "0",
      "Snow_Max": "0",
      "Humidity_Min": "52.9",
      "Humidity_Max": "87.9",
      "Precip_Min": "2",
      "Precip_Max": "8.334",
      "PrecipProb_Min": "0",
      "PrecipProb_Max": "100",
      "Pressure_Min": "1006",
      "Pressure_Max": "1033",
      "UVIndex_Min": "2",
      "UVIndex_Max": " 9",
      "Visibility_Min": " 11.8",
      "Visibility_Max": "16",
      "WindSpeed_Min": "7.6",
      "WindSpeed_Max": "26.2",
      "WindDirection_Min": "1.3",
      "WindDirection_Max": "354.6",
      "Sunrise_Max": " 06:27:57",
      "Sunrise_Min": "07:25:57",
      "Sunset_Max": "17:54:31",
      "Sunset_Min": "19:38:07",
      "Moonrise_Max": "01:20:57",
      "Moonrise_Min": "22:38:02",
      "Moonset_Max": "00:02:08",
      "Moonset_Min": "22:52:57"
    },
    {
      "Condition": "Cloudy",
      "Temperature_Min": " 5.6",
      "Temperature_Max": " 15",
      "Dew_Min": "4.1",
      "Dew_Max": "8.6",
      "Feelslike_Min": "5.9",
      "Feelslike_Max": "11.3",
      "Snow_Min": "0",
      "Snow_Max": "0",
      "Humidity_Min": "72",
      "Humidity_Max": "91.8",
      "Precip_Min": "1",
      "Precip_Max": "7.42",
      "PrecipProb_Min": "0",
      "PrecipProb_Max": "100",
      "Pressure_Min": "1008.9",
      "Pressure_Max": "1027",
      "UVIndex_Min": "1",
      "UVIndex_Max": " 6",
      "Visibility_Min": " 12.2",
      "Visibility_Max": "15.9",
      "WindSpeed_Min": "11.1",
      "WindSpeed_Max": "21.4",
      "WindDirection_Min": "152.1",
      "WindDirection_Max": "353.4",
      "Sunrise_Max": " 06:45:39",
      "Sunrise_Min": "07:23:57",
      "Sunset_Max": "17:56:01",
      "Sunset_Min": "19:36:41",
      "Moonrise_Max": "04:42:45",
      "Moonrise_Min": "23:59:18",
      "Moonset_Max": "06:20:39",
      "Moonset_Min": "19:18:46"
    }
  ],
  "Apr": [
    {
      "Condition": "Rain",
      "Temperature_Min": " 2.2",
      "Temperature_Max": " 15.9",
      "Dew_Min": "-0.3",
      "Dew_Max": "7.4",
      "Feelslike_Min": "1.8",
      "Feelslike_Max": "11.4",
      "Snow_Min": "0",
      "Snow_Max": "0.9",
      "Humidity_Min": "63.2",
      "Humidity_Max": "81.9",
      "Precip_Min": "0.023",
      "Precip_Max": "11.866",
      "PrecipProb_Min": "100",
      "PrecipProb_Max": "100",
      "Pressure_Min": "1003",
      "Pressure_Max": "1025.2",
      "UVIndex_Min": "1",
      "UVIndex_Max": " 10",
      "Visibility_Min": " 13.9",
      "Visibility_Max": "16",
      "WindSpeed_Min": "11.3",
      "WindSpeed_Max": "33.4",
      "WindDirection_Min": "135.7",
      "WindDirection_Max": "347.8",
      "Sunrise_Max": " 05:53:33",
      "Sunrise_Min": "06:47:34",
      "Sunset_Max": "19:39:32",
      "Sunset_Min": "20:20:25",
      "Moonrise_Max": "00:25:44",
      "Moonrise_Min": "23:03:29",
      "Moonset_Max": "02:57:39",
      "Moonset_Min": "23:54:32"
    },
    {
      "Condition": "Partially cloudy",
      "Temperature_Min": " 1",
      "Temperature_Max": " 19.2",
      "Dew_Min": "-0.3",
      "Dew_Max": "7.4",
      "Feelslike_Min": "1.8",
      "Feelslike_Max": "12",
      "Snow_Min": "0",
      "Snow_Max": "0.1",
      "Humidity_Min": "57.5",
      "Humidity_Max": "81.9",
      "Precip_Min": "2",
      "Precip_Max": "11.866",
      "PrecipProb_Min": "0",
      "PrecipProb_Max": "100",
      "Pressure_Min": "1003",
      "Pressure_Max": "1026.5",
      "UVIndex_Min": "5",
      "UVIndex_Max": " 9",
      "Visibility_Min": " 13.9",
      "Visibility_Max": "16",
      "WindSpeed_Min": "11.3",
      "WindSpeed_Max": "33.4",
      "WindDirection_Min": "123.8",
      "WindDirection_Max": "347.8",
      "Sunrise_Max": " 05:53:33",
      "Sunrise_Min": "06:47:34",
      "Sunset_Max": "19:39:32",
      "Sunset_Min": "20:20:25",
      "Moonrise_Max": "00:25:44",
      "Moonrise_Min": "21:39:10",
      "Moonset_Max": "02:57:39",
      "Moonset_Min": "23:54:32"
    },
    {
      "Condition": "Cloudy",
      "Temperature_Min": " 2.5",
      "Temperature_Max": " 13.6",
      "Dew_Min": "1.5",
      "Dew_Max": "6.7",
      "Feelslike_Min": "2.5",
      "Feelslike_Max": "10.9",
      "Snow_Min": "0",
      "Snow_Max": "0.9",
      "Humidity_Min": "73.6",
      "Humidity_Max": "79.2",
      "Precip_Min": "0.995",
      "Precip_Max": "4.472",
      "PrecipProb_Min": "100",
      "PrecipProb_Max": "100",
      "Pressure_Min": "1008.2",
      "Pressure_Max": "1018.3",
      "UVIndex_Min": "1",
      "UVIndex_Max": " 10",
      "Visibility_Min": " 14.4",
      "Visibility_Max": "15.6",
      "WindSpeed_Min": "23.6",
      "WindSpeed_Max": "28.4",
      "WindDirection_Min": "161.5",
      "WindDirection_Max": "193.4",
      "Sunrise_Max": " 06:02:00",
      "Sunrise_Min": "06:43:34",
      "Sunset_Max": "19:42:22",
      "Sunset_Min": "20:13:26",
      "Moonrise_Max": "04:28:30",
      "Moonrise_Min": "23:03:29",
      "Moonset_Max": "04:20:11",
      "Moonset_Min": "22:44:58"
    },
    {
      "Condition": "Sunny",
      "Temperature_Min": " 1.9",
      "Temperature_Max": " 22.7",
      "Dew_Min": "0.8",
      "Dew_Max": "4.2",
      "Feelslike_Min": "8.5",
      "Feelslike_Max": "14.4",
      "Snow_Min": "0",
      "Snow_Max": "0",
      "Humidity_Min": "54.3",
      "Humidity_Max": "61.1",
      "Precip_Min": "0",
      "Precip_Max": "0",
      "PrecipProb_Min": "0",
      "PrecipProb_Max": "0",
      "Pressure_Min": "1022.2",
      "Pressure_Max": "1031.1",
      "UVIndex_Min": "7",
      "UVIndex_Max": " 7",
      "Visibility_Min": " 16",
      "Visibility_Max": "16",
      "WindSpeed_Min": "11",
      "WindSpeed_Max": "14.2",
      "WindDirection_Min": "322.2",
      "WindDirection_Max": "340.9",
      "Sunrise_Max": " 06:35:38",
      "Sunrise_Min": "06:37:36",
      "Sunset_Max": "19:46:37",
      "Sunset_Min": "19:48:02",
      "Moonrise_Max": "09:15:44",
      "Moonrise_Min": "09:56:16",
      "Moonset_Max": "01:01:13",
      "Moonset_Min": "02:03:04"
    },
    {
      "Condition": "Snow",
      "Temperature_Min": " 2.2",
      "Temperature_Max": " 10.7",
      "Dew_Min": "0.2",
      "Dew_Max": "0.4",
      "Feelslike_Min": "1.8",
      "Feelslike_Max": "4.7",
      "Snow_Min": "0",
      "Snow_Max": "0.1",
      "Humidity_Min": "67.7",
      "Humidity_Max": "73",
      "Precip_Min": "0.023",
      "Precip_Max": "0.172",
      "PrecipProb_Min": "100",
      "PrecipProb_Max": "100",
      "Pressure_Min": "1013.5",
      "Pressure_Max": "1018.3",
      "UVIndex_Min": "6",
      "UVIndex_Max": " 7",
      "Visibility_Min": " 15.8",
      "Visibility_Max": "16",
      "WindSpeed_Min": "14",
      "WindSpeed_Max": "31.6",
      "WindDirection_Min": "170.6",
      "WindDirection_Max": "176",
      "Sunrise_Max": " 06:20:11",
      "Sunrise_Min": "06:25:54",
      "Sunset_Max": "19:55:06",
      "Sunset_Min": "19:59:21",
      "Moonrise_Max": "15:11:34",
      "Moonrise_Min": "18:56:29",
      "Moonset_Max": "05:14:42",
      "Moonset_Min": "06:11:56"
    }
  ],
  "May": [
    {
      "Condition": "Partially cloudy",
      "Temperature_Min": " 4.7",
      "Temperature_Max": " 21.3",
      "Dew_Min": "2",
      "Dew_Max": "11.2",
      "Feelslike_Min": "7.3",
      "Feelslike_Max": "15.3",
      "Snow_Min": "0",
      "Snow_Max": "0",
      "Humidity_Min": "58.2",
      "Humidity_Max": "84",
      "Precip_Min": "1",
      "Precip_Max": "8.328",
      "PrecipProb_Min": "0",
      "PrecipProb_Max": "100",
      "Pressure_Min": "1006.5",
      "Pressure_Max": "1024.5",
      "UVIndex_Min": "5",
      "UVIndex_Max": " 10",
      "Visibility_Min": " 13.5",
      "Visibility_Max": "16",
      "WindSpeed_Min": "11.2",
      "WindSpeed_Max": "33.5",
      "WindDirection_Min": "0.5",
      "WindDirection_Max": "339.6",
      "Sunrise_Max": " 05:16:19",
      "Sunrise_Min": "05:51:56",
      "Sunset_Max": "20:21:48",
      "Sunset_Min": "20:58:24",
      "Moonrise_Max": "00:31:50",
      "Moonrise_Min": "23:22:57",
      "Moonset_Max": "01:39:43",
      "Moonset_Min": "22:42:47"
    },
    {
      "Condition": "Rain",
      "Temperature_Min": " 4.8",
      "Temperature_Max": " 20.1",
      "Dew_Min": "3.6",
      "Dew_Max": "11.6",
      "Feelslike_Min": "7.3",
      "Feelslike_Max": "15.3",
      "Snow_Min": "0",
      "Snow_Max": "0",
      "Humidity_Min": "64.1",
      "Humidity_Max": "90.2",
      "Precip_Min": "0.025",
      "Precip_Max": "11.791",
      "PrecipProb_Min": "100",
      "PrecipProb_Max": "100",
      "Pressure_Min": "1006.5",
      "Pressure_Max": "1023.1",
      "UVIndex_Min": "2",
      "UVIndex_Max": " 10",
      "Visibility_Min": " 12.2",
      "Visibility_Max": "15.9",
      "WindSpeed_Min": "13.2",
      "WindSpeed_Max": "33.5",
      "WindDirection_Min": "35.2",
      "WindDirection_Max": "333.1",
      "Sunrise_Max": " 05:17:44",
      "Sunrise_Min": "05:50:20",
      "Sunset_Max": "20:23:10",
      "Sunset_Min": "20:56:28",
      "Moonrise_Max": "03:32:55",
      "Moonrise_Min": "20:34:34",
      "Moonset_Max": "00:50:10",
      "Moonset_Min": "22:47:49"
    },
    {
      "Condition": "Cloudy",
      "Temperature_Min": " 7.9",
      "Temperature_Max": " 15.7",
      "Dew_Min": "6.8",
      "Dew_Max": "11.6",
      "Feelslike_Min": "9",
      "Feelslike_Max": "13.2",
      "Snow_Min": "0",
      "Snow_Max": "0",
      "Humidity_Min": "72.9",
      "Humidity_Max": "90.2",
      "Precip_Min": "2",
      "Precip_Max": "11.791",
      "PrecipProb_Min": "0",
      "PrecipProb_Max": "100",
      "Pressure_Min": "1007.7",
      "Pressure_Max": "1024.5",
      "UVIndex_Min": "2",
      "UVIndex_Max": " 5",
      "Visibility_Min": " 12.2",
      "Visibility_Max": "16",
      "WindSpeed_Min": "13.3",
      "WindSpeed_Max": "27.2",
      "WindDirection_Min": "170.4",
      "WindDirection_Max": "235.5",
      "Sunrise_Max": " 05:17:44",
      "Sunrise_Min": "05:50:20",
      "Sunset_Max": "20:23:10",
      "Sunset_Min": "20:56:28",
      "Moonrise_Max": "03:15:51",
      "Moonrise_Min": "20:34:34",
      "Moonset_Max": "00:50:10",
      "Moonset_Min": "23:52:32"
    }
  ],
  "Jun": [
    {
      "Condition": "Rain",
      "Temperature_Min": " 9",
      "Temperature_Max": " 23.1",
      "Dew_Min": "7.4",
      "Dew_Max": "13.8",
      "Feelslike_Min": "11.9",
      "Feelslike_Max": "17.3",
      "Snow_Min": "0",
      "Snow_Max": "0",
      "Humidity_Min": "69.5",
      "Humidity_Max": "86.3",
      "Precip_Min": "0.025",
      "Precip_Max": "19.574",
      "PrecipProb_Min": "100",
      "PrecipProb_Max": "100",
      "Pressure_Min": "1006.8",
      "Pressure_Max": "1022.4",
      "UVIndex_Min": "2",
      "UVIndex_Max": " 10",
      "Visibility_Min": " 11",
      "Visibility_Max": "16",
      "WindSpeed_Min": "10.5",
      "WindSpeed_Max": "25.5",
      "WindDirection_Min": "5.4",
      "WindDirection_Max": "329.6",
      "Sunrise_Max": " 05:11:05",
      "Sunrise_Min": "05:15:41",
      "Sunset_Max": "20:59:20",
      "Sunset_Min": "21:11:01",
      "Moonrise_Max": "00:01:05",
      "Moonrise_Min": "22:11:16",
      "Moonset_Max": "00:18:14",
      "Moonset_Min": "23:35:35"
    },
    {
      "Condition": "Partially cloudy",
      "Temperature_Min": " 10",
      "Temperature_Max": " 24.4",
      "Dew_Min": "6.7",
      "Dew_Max": "13.3",
      "Feelslike_Min": "13.4",
      "Feelslike_Max": "18.1",
      "Snow_Min": "0",
      "Snow_Max": "0",
      "Humidity_Min": "56.1",
      "Humidity_Max": "85.8",
      "Precip_Min": "1",
      "Precip_Max": "19.574",
      "PrecipProb_Min": "0",
      "PrecipProb_Max": "100",
      "Pressure_Min": "1007.3",
      "Pressure_Max": "1026.4",
      "UVIndex_Min": "2",
      "UVIndex_Max": " 10",
      "Visibility_Min": " 11",
      "Visibility_Max": "16",
      "WindSpeed_Min": "8.4",
      "WindSpeed_Max": "25.5",
      "WindDirection_Min": "5.4",
      "WindDirection_Max": "337.1",
      "Sunrise_Max": " 05:11:05",
      "Sunrise_Min": "05:15:41",
      "Sunset_Max": "20:59:20",
      "Sunset_Min": "21:11:04",
      "Moonrise_Max": "00:01:05",
      "Moonrise_Min": "23:14:27",
      "Moonset_Max": "00:52:49",
      "Moonset_Min": "23:35:35"
    },
    {
      "Condition": "Cloudy",
      "Temperature_Min": " 9",
      "Temperature_Max": " 19.2",
      "Dew_Min": "7.4",
      "Dew_Max": "13.8",
      "Feelslike_Min": "11.9",
      "Feelslike_Max": "16.2",
      "Snow_Min": "0",
      "Snow_Max": "0",
      "Humidity_Min": "69.6",
      "Humidity_Max": "86.3",
      "Precip_Min": "0",
      "Precip_Max": "12.213",
      "PrecipProb_Min": "0",
      "PrecipProb_Max": "100",
      "Pressure_Min": "1006.8",
      "Pressure_Max": "1022.4",
      "UVIndex_Min": "5",
      "UVIndex_Max": " 10",
      "Visibility_Min": " 14.8",
      "Visibility_Max": "16",
      "WindSpeed_Min": "11.4",
      "WindSpeed_Max": "23.7",
      "WindDirection_Min": "178.4",
      "WindDirection_Max": "216.5",
      "Sunrise_Max": " 05:11:08",
      "Sunrise_Min": "05:14:31",
      "Sunset_Max": "21:01:06",
      "Sunset_Min": "21:10:19",
      "Moonrise_Max": "00:35:01",
      "Moonrise_Min": "22:11:16",
      "Moonset_Max": "00:18:14",
      "Moonset_Min": "11:22:11"
    },
    {
      "Condition": "Sunny",
      "Temperature_Min": " 10.8",
      "Temperature_Max": " 32.7",
      "Dew_Min": "7.1",
      "Dew_Max": "12",
      "Feelslike_Min": "18.1",
      "Feelslike_Max": "24.5",
      "Snow_Min": "0",
      "Snow_Max": "0",
      "Humidity_Min": "42.7",
      "Humidity_Max": "51.1",
      "Precip_Min": "0",
      "Precip_Max": "0",
      "PrecipProb_Min": "0",
      "PrecipProb_Max": "0",
      "Pressure_Min": "1013.6",
      "Pressure_Max": "1022",
      "UVIndex_Min": "9",
      "UVIndex_Max": " 9",
      "Visibility_Min": " 16",
      "Visibility_Max": "16",
      "WindSpeed_Min": "17.7",
      "WindSpeed_Max": "26.6",
      "WindDirection_Min": "234.9",
      "WindDirection_Max": "341",
      "Sunrise_Max": " 05:12:31",
      "Sunrise_Min": "05:13:43",
      "Sunset_Max": "21:11:07",
      "Sunset_Min": "21:11:10",
      "Moonrise_Max": "02:31:02",
      "Moonrise_Min": "03:49:59",
      "Moonset_Max": "17:19:31",
      "Moonset_Min": "20:36:13"
    }
  ],
  "Jul": [
    {
      "Condition": "Sunny",
      "Temperature_Min": " 13.4",
      "Temperature_Max": " 34",
      "Dew_Min": "10.2",
      "Dew_Max": "16.5",
      "Feelslike_Min": "18.5",
      "Feelslike_Max": "26.5",
      "Snow_Min": "0",
      "Snow_Max": "0",
      "Humidity_Min": "51.6",
      "Humidity_Max": "66.2",
      "Precip_Min": "0",
      "Precip_Max": "0",
      "PrecipProb_Min": "0",
      "PrecipProb_Max": "0",
      "Pressure_Min": "1011.4",
      "Pressure_Max": "1020.7",
      "UVIndex_Min": "9",
      "UVIndex_Max": " 9",
      "Visibility_Min": " 15.4",
      "Visibility_Max": "16",
      "WindSpeed_Min": "10.6",
      "WindSpeed_Max": "24.7",
      "WindDirection_Min": "287.5",
      "WindDirection_Max": "342.6",
      "Sunrise_Max": " 05:15:51",
      "Sunrise_Min": "05:45:47",
      "Sunset_Max": "20:44:53",
      "Sunset_Min": "21:10:28",
      "Moonrise_Max": "00:01:11",
      "Moonrise_Min": "22:30:41",
      "Moonset_Max": "02:45:11",
      "Moonset_Min": "23:24:04"
    },
    {
      "Condition": "Partially cloudy",
      "Temperature_Min": " 11.2",
      "Temperature_Max": " 25.2",
      "Dew_Min": "10.6",
      "Dew_Max": "13.1",
      "Feelslike_Min": "15.6",
      "Feelslike_Max": "19.8",
      "Snow_Min": "0",
      "Snow_Max": "0",
      "Humidity_Min": "61.7",
      "Humidity_Max": "77.3",
      "Precip_Min": "0",
      "Precip_Max": "0.363",
      "PrecipProb_Min": "0",
      "PrecipProb_Max": "100",
      "Pressure_Min": "1013.9",
      "Pressure_Max": "1026.6",
      "UVIndex_Min": "7",
      "UVIndex_Max": " 10",
      "Visibility_Min": " 14.4",
      "Visibility_Max": "16",
      "WindSpeed_Min": "11",
      "WindSpeed_Max": "18.6",
      "WindDirection_Min": "202.2",
      "WindDirection_Max": "328.9",
      "Sunrise_Max": " 05:16:29",
      "Sunrise_Min": "05:36:05",
      "Sunset_Max": "20:54:56",
      "Sunset_Min": "21:10:12",
      "Moonrise_Max": "00:56:34",
      "Moonrise_Min": "23:00:56",
      "Moonset_Max": "00:07:24",
      "Moonset_Min": "23:47:48"
    },
    {
      "Condition": "Rain",
      "Temperature_Min": " 12.6",
      "Temperature_Max": " 26.9",
      "Dew_Min": "11.6",
      "Dew_Max": "14.7",
      "Feelslike_Min": "13.8",
      "Feelslike_Max": "20.6",
      "Snow_Min": "0",
      "Snow_Max": "0",
      "Humidity_Min": "64.9",
      "Humidity_Max": "88",
      "Precip_Min": "0.173",
      "Precip_Max": "1.463",
      "PrecipProb_Min": "100",
      "PrecipProb_Max": "100",
      "Pressure_Min": "1013.8",
      "Pressure_Max": "1020.4",
      "UVIndex_Min": "1",
      "UVIndex_Max": " 9",
      "Visibility_Min": " 13.8",
      "Visibility_Max": "15.8",
      "WindSpeed_Min": "12.3",
      "WindSpeed_Max": "15.5",
      "WindDirection_Min": "163.3",
      "WindDirection_Max": "328.9",
      "Sunrise_Max": " 05:17:08",
      "Sunrise_Min": "05:33:47",
      "Sunset_Max": "20:57:07",
      "Sunset_Min": "21:09:53",
      "Moonrise_Max": "00:36:06",
      "Moonrise_Min": "13:05:58",
      "Moonset_Max": "00:24:54",
      "Moonset_Min": "15:09:59"
    },
    {
      "Condition": "Cloudy",
      "Temperature_Min": " 13",
      "Temperature_Max": " 22.3",
      "Dew_Min": "9.3",
      "Dew_Max": "14.7",
      "Feelslike_Min": "13.8",
      "Feelslike_Max": "18.8",
      "Snow_Min": "0",
      "Snow_Max": "0",
      "Humidity_Min": "60.5",
      "Humidity_Max": "88",
      "Precip_Min": "0",
      "Precip_Max": "1.463",
      "PrecipProb_Min": "0",
      "PrecipProb_Max": "100",
      "Pressure_Min": "1013.8",
      "Pressure_Max": "1018.6",
      "UVIndex_Min": "1",
      "UVIndex_Max": " 8",
      "Visibility_Min": " 13.8",
      "Visibility_Max": "16",
      "WindSpeed_Min": "10.3",
      "WindSpeed_Max": "15.8",
      "WindDirection_Min": "3.5",
      "WindDirection_Max": "233.6",
      "Sunrise_Max": " 05:17:08",
      "Sunrise_Min": "05:29:25",
      "Sunset_Max": "21:01:04",
      "Sunset_Min": "21:09:53",
      "Moonrise_Max": "09:36:55",
      "Moonrise_Min": "23:43:54",
      "Moonset_Max": "00:41:36",
      "Moonset_Min": "10:19:11"
    }
  ],
  "Aug": [
    {
      "Condition": "Sunny",
      "Temperature_Min": " 12.3",
      "Temperature_Max": " 31.7",
      "Dew_Min": "10.7",
      "Dew_Max": "15.6",
      "Feelslike_Min": "18",
      "Feelslike_Max": "24.1",
      "Snow_Min": "0",
      "Snow_Max": "0",
      "Humidity_Min": "55.1",
      "Humidity_Max": "68.2",
      "Precip_Min": "0",
      "Precip_Max": "0",
      "PrecipProb_Min": "0",
      "PrecipProb_Max": "0",
      "Pressure_Min": "1013.2",
      "Pressure_Max": "1020.3",
      "UVIndex_Min": "7",
      "UVIndex_Max": " 10",
      "Visibility_Min": " 15.4",
      "Visibility_Max": "16",
      "WindSpeed_Min": "10.2",
      "WindSpeed_Max": "25.2",
      "WindDirection_Min": "196.6",
      "WindDirection_Max": "340.4",
      "Sunrise_Max": " 05:47:02",
      "Sunrise_Min": "06:26:44",
      "Sunset_Max": "19:51:31",
      "Sunset_Min": "20:43:29",
      "Moonrise_Max": "01:08:34",
      "Moonrise_Min": "22:59:18",
      "Moonset_Max": "00:06:04",
      "Moonset_Min": "22:47:55"
    },
    {
      "Condition": "Partially cloudy",
      "Temperature_Min": " 13",
      "Temperature_Max": " 30.7",
      "Dew_Min": "10.9",
      "Dew_Max": "17",
      "Feelslike_Min": "17.3",
      "Feelslike_Max": "26",
      "Snow_Min": "0",
      "Snow_Max": "0",
      "Humidity_Min": "56.1",
      "Humidity_Max": "76.7",
      "Precip_Min": "0.2",
      "Precip_Max": "0.547",
      "PrecipProb_Min": "0",
      "PrecipProb_Max": "100",
      "Pressure_Min": "1012.5",
      "Pressure_Max": "1021.3",
      "UVIndex_Min": "2",
      "UVIndex_Max": " 10",
      "Visibility_Min": " 15.3",
      "Visibility_Max": "16",
      "WindSpeed_Min": "10.5",
      "WindSpeed_Max": "23.2",
      "WindDirection_Min": "186.2",
      "WindDirection_Max": "328.9",
      "Sunrise_Max": " 05:48:18",
      "Sunrise_Min": "06:13:20",
      "Sunset_Max": "20:10:35",
      "Sunset_Min": "20:42:04",
      "Moonrise_Max": "00:24:39",
      "Moonrise_Min": "23:50:11",
      "Moonset_Max": "02:21:20",
      "Moonset_Min": "23:41:52"
    },
    {
      "Condition": "Rain",
      "Temperature_Min": " 15.9",
      "Temperature_Max": " 26.1",
      "Dew_Min": "14.4",
      "Dew_Max": "17",
      "Feelslike_Min": "18.6",
      "Feelslike_Max": "22.4",
      "Snow_Min": "0",
      "Snow_Max": "0",
      "Humidity_Min": "72.3",
      "Humidity_Max": "76.7",
      "Precip_Min": "0.119",
      "Precip_Max": "0.547",
      "PrecipProb_Min": "100",
      "PrecipProb_Max": "100",
      "Pressure_Min": "1012.9",
      "Pressure_Max": "1017.2",
      "UVIndex_Min": "6",
      "UVIndex_Max": " 6",
      "Visibility_Min": " 16",
      "Visibility_Max": "16",
      "WindSpeed_Min": "15",
      "WindSpeed_Max": "16.4",
      "WindDirection_Min": "186.2",
      "WindDirection_Max": "192.2",
      "Sunrise_Max": " 05:58:42",
      "Sunrise_Min": "06:10:40",
      "Sunset_Max": "20:14:14",
      "Sunset_Min": "20:29:46",
      "Moonrise_Max": "20:23:04",
      "Moonrise_Min": "23:50:11",
      "Moonset_Max": "03:36:29",
      "Moonset_Min": "15:16:20"
    },
    {
      "Condition": "Cloudy",
      "Temperature_Min": " 14.2",
      "Temperature_Max": " 22.2",
      "Dew_Min": "11.5",
      "Dew_Max": "14.1",
      "Feelslike_Min": "17.1",
      "Feelslike_Max": "18.7",
      "Snow_Min": "0",
      "Snow_Max": "0",
      "Humidity_Min": "71.3",
      "Humidity_Max": "75.3",
      "Precip_Min": "0",
      "Precip_Max": "0",
      "PrecipProb_Min": "0",
      "PrecipProb_Max": "0",
      "Pressure_Min": "1014.9",
      "Pressure_Max": "1015.5",
      "UVIndex_Min": "5",
      "UVIndex_Max": " 6",
      "Visibility_Min": " 15.3",
      "Visibility_Max": "16",
      "WindSpeed_Min": "15.9",
      "WindSpeed_Max": "19.8",
      "WindDirection_Min": "195.4",
      "WindDirection_Max": "197.5",
      "Sunrise_Max": " 06:20:02",
      "Sunrise_Min": "06:21:22",
      "Sunset_Max": "19:59:17",
      "Sunset_Min": "20:01:12",
      "Moonrise_Max": "05:17:46",
      "Moonrise_Min": "06:27:15",
      "Moonset_Max": "20:18:49",
      "Moonset_Min": "20:37:37"
    }
  ],
  "Sep": [
    {
      "Condition": "Partially cloudy",
      "Temperature_Min": " 10.9",
      "Temperature_Max": " 24.7",
      "Dew_Min": "8.4",
      "Dew_Max": "14.6",
      "Feelslike_Min": "14.8",
      "Feelslike_Max": "20",
      "Snow_Min": "0",
      "Snow_Max": "0",
      "Humidity_Min": "59.9",
      "Humidity_Max": "82.8",
      "Precip_Min": "0.1",
      "Precip_Max": "0.565",
      "PrecipProb_Min": "0",
      "PrecipProb_Max": "100",
      "Pressure_Min": "1011.4",
      "Pressure_Max": "1023.1",
      "UVIndex_Min": "4",
      "UVIndex_Max": " 8",
      "Visibility_Min": " 12.7",
      "Visibility_Max": "16",
      "WindSpeed_Min": "10.2",
      "WindSpeed_Max": "27.1",
      "WindDirection_Min": "161.6",
      "WindDirection_Max": "352",
      "Sunrise_Max": " 06:28:04",
      "Sunrise_Min": "07:07:10",
      "Sunset_Max": "18:50:29",
      "Sunset_Min": "19:49:32",
      "Moonrise_Max": "03:02:32",
      "Moonrise_Min": "23:01:17",
      "Moonset_Max": "00:07:22",
      "Moonset_Min": "23:16:00"
    },
    {
      "Condition": "Sunny",
      "Temperature_Min": " 9.9",
      "Temperature_Max": " 30.1",
      "Dew_Min": "6.2",
      "Dew_Max": "13.9",
      "Feelslike_Min": "16.7",
      "Feelslike_Max": "21.3",
      "Snow_Min": "0",
      "Snow_Max": "0",
      "Humidity_Min": "45.5",
      "Humidity_Max": "73.4",
      "Precip_Min": "0",
      "Precip_Max": "0",
      "PrecipProb_Min": "0",
      "PrecipProb_Max": "0",
      "Pressure_Min": "1008.4",
      "Pressure_Max": "1022.6",
      "UVIndex_Min": "6",
      "UVIndex_Max": " 8",
      "Visibility_Min": " 11.8",
      "Visibility_Max": "16",
      "WindSpeed_Min": "7.9",
      "WindSpeed_Max": "24.8",
      "WindDirection_Min": "0.2",
      "WindDirection_Max": "351.5",
      "Sunrise_Max": " 06:29:24",
      "Sunrise_Min": "07:03:03",
      "Sunset_Max": "18:56:36",
      "Sunset_Min": "19:47:34",
      "Moonrise_Max": "00:49:07",
      "Moonrise_Min": "23:51:03",
      "Moonset_Max": "01:14:25",
      "Moonset_Min": "22:37:22"
    },
    {
      "Condition": "Rain",
      "Temperature_Min": " 12.8",
      "Temperature_Max": " 24.2",
      "Dew_Min": "9.6",
      "Dew_Max": "13.5",
      "Feelslike_Min": "15.2",
      "Feelslike_Max": "18.7",
      "Snow_Min": "0",
      "Snow_Max": "0",
      "Humidity_Min": "68.3",
      "Humidity_Max": "82.8",
      "Precip_Min": "0.045",
      "Precip_Max": "1.333",
      "PrecipProb_Min": "100",
      "PrecipProb_Max": "100",
      "Pressure_Min": "1015.4",
      "Pressure_Max": "1018.2",
      "UVIndex_Min": "4",
      "UVIndex_Max": " 9",
      "Visibility_Min": " 12.7",
      "Visibility_Max": "15.7",
      "WindSpeed_Min": "14.7",
      "WindSpeed_Max": "23",
      "WindDirection_Min": "133.1",
      "WindDirection_Max": "181.1",
      "Sunrise_Max": " 06:30:44",
      "Sunrise_Min": "07:04:25",
      "Sunset_Max": "18:54:33",
      "Sunset_Min": "19:45:34",
      "Moonrise_Max": "10:17:40",
      "Moonrise_Min": "22:20:35",
      "Moonset_Max": "14:09:44",
      "Moonset_Min": "23:16:00"
    },
    {
      "Condition": "Cloudy",
      "Temperature_Min": " 13.3",
      "Temperature_Max": " 21.3",
      "Dew_Min": "9.6",
      "Dew_Max": "12.4",
      "Feelslike_Min": "15.5",
      "Feelslike_Max": "18.7",
      "Snow_Min": "0",
      "Snow_Max": "0",
      "Humidity_Min": "64.4",
      "Humidity_Max": "68.3",
      "Precip_Min": "0.1",
      "Precip_Max": "1.333",
      "PrecipProb_Min": "0",
      "PrecipProb_Max": "100",
      "Pressure_Min": "1012.2",
      "Pressure_Max": "1018.2",
      "UVIndex_Min": "6",
      "UVIndex_Max": " 9",
      "Visibility_Min": " 15.7",
      "Visibility_Max": "15.8",
      "WindSpeed_Min": "9.4",
      "WindSpeed_Max": "14.9",
      "WindDirection_Min": "133.1",
      "WindDirection_Max": "317.4",
      "Sunrise_Max": " 06:44:08",
      "Sunrise_Min": "06:48:09",
      "Sunset_Max": "19:19:11",
      "Sunset_Min": "19:25:20",
      "Moonrise_Max": "21:01:04",
      "Moonrise_Min": "22:20:35",
      "Moonset_Max": "10:35:16",
      "Moonset_Min": "14:09:44"
    }
  ],
  "Oct": [
    {
      "Condition": "Sunny",
      "Temperature_Min": " 8.6",
      "Temperature_Max": " 29",
      "Dew_Min": "8.5",
      "Dew_Max": "12.5",
      "Feelslike_Min": "14.4",
      "Feelslike_Max": "18.4",
      "Snow_Min": "0",
      "Snow_Max": "0",
      "Humidity_Min": "59.2",
      "Humidity_Max": "76.6",
      "Precip_Min": "0",
      "Precip_Max": "0",
      "PrecipProb_Min": "0",
      "PrecipProb_Max": "0",
      "Pressure_Min": "1014",
      "Pressure_Max": "1023.5",
      "UVIndex_Min": "5",
      "UVIndex_Max": " 6",
      "Visibility_Min": " 8.7",
      "Visibility_Max": "15.9",
      "WindSpeed_Min": "11.3",
      "WindSpeed_Max": "17.3",
      "WindDirection_Min": "159.5",
      "WindDirection_Max": "339.7",
      "Sunrise_Max": " 07:08:33",
      "Sunrise_Min": "07:31:15",
      "Sunset_Max": "18:17:14",
      "Sunset_Min": "18:48:28",
      "Moonrise_Max": "14:14:09",
      "Moonrise_Min": "23:38:19",
      "Moonset_Max": "04:21:34",
      "Moonset_Min": "23:02:33"
    },
    {
      "Condition": "Partially cloudy",
      "Temperature_Min": " 5.8",
      "Temperature_Max": " 22.1",
      "Dew_Min": "5.9",
      "Dew_Max": "12.7",
      "Feelslike_Min": "7.8",
      "Feelslike_Max": "16.2",
      "Snow_Min": "0",
      "Snow_Max": "0",
      "Humidity_Min": "76.4",
      "Humidity_Max": "89.4",
      "Precip_Min": "0",
      "Precip_Max": "8.233",
      "PrecipProb_Min": "0",
      "PrecipProb_Max": "100",
      "Pressure_Min": "1007.9",
      "Pressure_Max": "1025.4",
      "UVIndex_Min": "1",
      "UVIndex_Max": " 6",
      "Visibility_Min": " 3.5",
      "Visibility_Max": "16",
      "WindSpeed_Min": "8.5",
      "WindSpeed_Max": "24.4",
      "WindDirection_Min": "11.6",
      "WindDirection_Max": "334",
      "Sunrise_Max": " 07:12:43",
      "Sunrise_Min": "07:49:05",
      "Sunset_Max": "17:56:16",
      "Sunset_Min": "18:42:25",
      "Moonrise_Max": "00:44:55",
      "Moonrise_Min": "19:03:33",
      "Moonset_Max": "00:16:06",
      "Moonset_Min": "20:54:20"
    },
    {
      "Condition": "Rain",
      "Temperature_Min": " 5.9",
      "Temperature_Max": " 20.8",
      "Dew_Min": "5.7",
      "Dew_Max": "11.1",
      "Feelslike_Min": "7.8",
      "Feelslike_Max": "15.5",
      "Snow_Min": "0",
      "Snow_Max": "0",
      "Humidity_Min": "76.4",
      "Humidity_Max": "89.4",
      "Precip_Min": "0.045",
      "Precip_Max": "19.624",
      "PrecipProb_Min": "100",
      "PrecipProb_Max": "100",
      "Pressure_Min": "1007.9",
      "Pressure_Max": "1019.9",
      "UVIndex_Min": "1",
      "UVIndex_Max": " 5",
      "Visibility_Min": " 11.9",
      "Visibility_Max": "16",
      "WindSpeed_Min": "9.9",
      "WindSpeed_Max": "29.6",
      "WindDirection_Min": "134.5",
      "WindDirection_Max": "201.4",
      "Sunrise_Max": " 07:21:10",
      "Sunrise_Min": "07:52:06",
      "Sunset_Max": "17:53:03",
      "Sunset_Min": "18:30:34",
      "Moonrise_Max": "03:04:26",
      "Moonrise_Min": "19:03:33",
      "Moonset_Max": "08:12:42",
      "Moonset_Min": "23:25:04"
    },
    {
      "Condition": "Cloudy",
      "Temperature_Min": " 6.5",
      "Temperature_Max": " 15.9",
      "Dew_Min": "5.7",
      "Dew_Max": "8.2",
      "Feelslike_Min": "7.9",
      "Feelslike_Max": "13.1",
      "Snow_Min": "0",
      "Snow_Max": "0",
      "Humidity_Min": "61.6",
      "Humidity_Max": "82.8",
      "Precip_Min": "1",
      "Precip_Max": "19.624",
      "PrecipProb_Min": "0",
      "PrecipProb_Max": "100",
      "Pressure_Min": "1010.4",
      "Pressure_Max": "1019.3",
      "UVIndex_Min": "1",
      "UVIndex_Max": " 7",
      "Visibility_Min": " 14.1",
      "Visibility_Max": "16",
      "WindSpeed_Min": "15.7",
      "WindSpeed_Max": "32.2",
      "WindDirection_Min": "167.1",
      "WindDirection_Max": "183.5",
      "Sunrise_Max": " 07:37:07",
      "Sunrise_Min": "07:52:06",
      "Sunset_Max": "17:53:03",
      "Sunset_Min": "18:09:57",
      "Moonrise_Max": "03:04:26",
      "Moonrise_Min": "14:58:13",
      "Moonset_Max": "17:06:03",
      "Moonset_Min": "23:25:04"
    }
  ],
  "Nov": [
    {
      "Condition": "Rain",
      "Temperature_Min": " -0.4",
      "Temperature_Max": " 15",
      "Dew_Min": "-1.7",
      "Dew_Max": "9.9",
      "Feelslike_Min": "-1.7",
      "Feelslike_Max": "11.1",
      "Snow_Min": "0",
      "Snow_Max": "1.4",
      "Humidity_Min": "70.5",
      "Humidity_Max": "91.5",
      "Precip_Min": "0.064",
      "Precip_Max": "23.559",
      "PrecipProb_Min": "100",
      "PrecipProb_Max": "100",
      "Pressure_Min": "999.4",
      "Pressure_Max": "1028.1",
      "UVIndex_Min": "0",
      "UVIndex_Max": " 4",
      "Visibility_Min": " 9.1",
      "Visibility_Max": "16",
      "WindSpeed_Min": "11.9",
      "WindSpeed_Max": "33.6",
      "WindDirection_Min": "6.3",
      "WindDirection_Max": "326.7",
      "Sunrise_Max": " 07:01:13",
      "Sunrise_Min": "07:59:42",
      "Sunset_Max": "16:20:17",
      "Sunset_Min": "17:51:30",
      "Moonrise_Max": "05:52:05",
      "Moonrise_Min": "16:50:55",
      "Moonset_Max": "00:46:32",
      "Moonset_Min": "22:55:54"
    },
    {
      "Condition": "Partially cloudy",
      "Temperature_Min": " -1.3",
      "Temperature_Max": " 11.4",
      "Dew_Min": "-2.5",
      "Dew_Max": "6.1",
      "Feelslike_Min": "0.9",
      "Feelslike_Max": "8.3",
      "Snow_Min": "0",
      "Snow_Max": "0",
      "Humidity_Min": "64.4",
      "Humidity_Max": "87",
      "Precip_Min": "1",
      "Precip_Max": "14.998",
      "PrecipProb_Min": "0",
      "PrecipProb_Max": "100",
      "Pressure_Min": "1007",
      "Pressure_Max": "1033.3",
      "UVIndex_Min": "0",
      "UVIndex_Max": " 5",
      "Visibility_Min": " 11.6",
      "Visibility_Max": "16",
      "WindSpeed_Min": "7.4",
      "WindSpeed_Max": "31.3",
      "WindDirection_Min": "2.8",
      "WindDirection_Max": "349.4",
      "Sunrise_Max": " 07:04:16",
      "Sunrise_Min": "07:59:42",
      "Sunset_Max": "16:22:00",
      "Sunset_Min": "17:51:30",
      "Moonrise_Max": "03:17:13",
      "Moonrise_Min": "23:45:46",
      "Moonset_Max": "04:40:10",
      "Moonset_Min": "20:10:13"
    },
    {
      "Condition": "Cloudy",
      "Temperature_Min": " -0.4",
      "Temperature_Max": " 15",
      "Dew_Min": "-1.7",
      "Dew_Max": "9.9",
      "Feelslike_Min": "-1.7",
      "Feelslike_Max": "11.1",
      "Snow_Min": "0",
      "Snow_Max": "1.4",
      "Humidity_Min": "63.7",
      "Humidity_Max": "91.5",
      "Precip_Min": "1",
      "Precip_Max": "23.559",
      "PrecipProb_Min": "0",
      "PrecipProb_Max": "100",
      "Pressure_Min": "999.4",
      "Pressure_Max": "1028.1",
      "UVIndex_Min": "0",
      "UVIndex_Max": " 4",
      "Visibility_Min": " 9.1",
      "Visibility_Max": "15.8",
      "WindSpeed_Min": "8.7",
      "WindSpeed_Max": "33.6",
      "WindDirection_Min": "6.3",
      "WindDirection_Max": "326.7",
      "Sunrise_Max": " 07:01:13",
      "Sunrise_Min": "07:58:11",
      "Sunset_Max": "16:20:17",
      "Sunset_Min": "17:49:57",
      "Moonrise_Max": "04:32:09",
      "Moonrise_Min": "16:34:00",
      "Moonset_Max": "00:46:32",
      "Moonset_Min": "22:55:54"
    },
    {
      "Condition": "Sunny",
      "Temperature_Min": " -2.4",
      "Temperature_Max": " 11.6",
      "Dew_Min": "-5.5",
      "Dew_Max": "3.2",
      "Feelslike_Min": "2",
      "Feelslike_Max": "5.3",
      "Snow_Min": "0",
      "Snow_Max": "0",
      "Humidity_Min": "54.6",
      "Humidity_Max": "85",
      "Precip_Min": "0",
      "Precip_Max": "0",
      "PrecipProb_Min": "0",
      "PrecipProb_Max": "0",
      "Pressure_Min": "1023.9",
      "Pressure_Max": "1033.4",
      "UVIndex_Min": "4",
      "UVIndex_Max": " 4",
      "Visibility_Min": " 13.1",
      "Visibility_Max": "15.9",
      "WindSpeed_Min": "8.9",
      "WindSpeed_Max": "19.8",
      "WindDirection_Min": "73.2",
      "WindDirection_Max": "355.7",
      "Sunrise_Max": " 07:10:19",
      "Sunrise_Min": "07:27:44",
      "Sunset_Max": "16:24:06",
      "Sunset_Min": "16:36:09",
      "Moonrise_Max": "00:54:44",
      "Moonrise_Min": "22:36:38",
      "Moonset_Max": "11:43:30",
      "Moonset_Min": "16:48:24"
    },
    {
      "Condition": "Snow",
      "Temperature_Min": " -0.4",
      "Temperature_Max": " 5.6",
      "Dew_Min": "-1.7",
      "Dew_Max": "1.3",
      "Feelslike_Min": "-1.7",
      "Feelslike_Max": "2",
      "Snow_Min": "0",
      "Snow_Max": "1.4",
      "Humidity_Min": "70.6",
      "Humidity_Max": "91.5",
      "Precip_Min": "0.154",
      "Precip_Max": "17.699",
      "PrecipProb_Min": "100",
      "PrecipProb_Max": "100",
      "Pressure_Min": "999.4",
      "Pressure_Max": "1012.7",
      "UVIndex_Min": "0",
      "UVIndex_Max": " 4",
      "Visibility_Min": " 9.1",
      "Visibility_Max": "15.8",
      "WindSpeed_Min": "16",
      "WindSpeed_Max": "26.6",
      "WindDirection_Min": "133.1",
      "WindDirection_Max": "326.7",
      "Sunrise_Max": " 07:33:05",
      "Sunrise_Min": "07:35:38",
      "Sunset_Max": "16:20:17",
      "Sunset_Min": "16:21:23",
      "Moonrise_Max": "12:33:41",
      "Moonrise_Min": "13:23:18",
      "Moonset_Max": "21:34:08",
      "Moonset_Min": "22:55:54"
    }
  ],
  "Dec": [
    {
      "Condition": "Snow",
      "Temperature_Min": " -3",
      "Temperature_Max": " 7.3",
      "Dew_Min": "-2.8",
      "Dew_Max": "1.1",
      "Feelslike_Min": "-1.9",
      "Feelslike_Max": "1.6",
      "Snow_Min": "0",
      "Snow_Max": "4",
      "Humidity_Min": "77.8",
      "Humidity_Max": "96",
      "Precip_Min": "0.09",
      "Precip_Max": "8.502",
      "PrecipProb_Min": "100",
      "PrecipProb_Max": "100",
      "Pressure_Min": "1007.1",
      "Pressure_Max": "1024.1",
      "UVIndex_Min": "0",
      "UVIndex_Max": " 4",
      "Visibility_Min": " 5.9",
      "Visibility_Max": "14.5",
      "WindSpeed_Min": "6.3",
      "WindSpeed_Max": "24.2",
      "WindDirection_Min": "3.2",
      "WindDirection_Max": "359.9",
      "Sunrise_Max": " 07:36:53",
      "Sunrise_Min": "07:54:23",
      "Sunset_Max": "16:18:39",
      "Sunset_Min": "16:19:49",
      "Moonrise_Max": "00:55:58",
      "Moonrise_Min": "14:32:11",
      "Moonset_Max": "00:14:20",
      "Moonset_Min": "14:04:16"
    },
    {
      "Condition": "Partially cloudy",
      "Temperature_Min": " -7.9",
      "Temperature_Max": " 11.3",
      "Dew_Min": "-14",
      "Dew_Max": "9.1",
      "Feelslike_Min": "-9.8",
      "Feelslike_Max": "9.6",
      "Snow_Min": "0",
      "Snow_Max": "2.1",
      "Humidity_Min": "52.1",
      "Humidity_Max": "95.3",
      "Precip_Min": "0.1",
      "Precip_Max": "7.901",
      "PrecipProb_Min": "0",
      "PrecipProb_Max": "100",
      "Pressure_Min": "1007.1",
      "Pressure_Max": "1033.2",
      "UVIndex_Min": "1",
      "UVIndex_Max": " 4",
      "Visibility_Min": " 11.5",
      "Visibility_Max": "16",
      "WindSpeed_Min": "4.6",
      "WindSpeed_Max": "29.4",
      "WindDirection_Min": "3.2",
      "WindDirection_Max": "185.9",
      "Sunrise_Max": " 07:36:53",
      "Sunrise_Min": "07:57:20",
      "Sunset_Max": "16:17:47",
      "Sunset_Min": "16:24:52",
      "Moonrise_Max": "06:07:02",
      "Moonrise_Min": "23:47:06",
      "Moonset_Max": "00:14:20",
      "Moonset_Min": "23:19:02"
    },
    {
      "Condition": "Rain",
      "Temperature_Min": " -4.2",
      "Temperature_Max": " 12.4",
      "Dew_Min": "-3",
      "Dew_Max": "9.1",
      "Feelslike_Min": "-5.1",
      "Feelslike_Max": "9.8",
      "Snow_Min": "0",
      "Snow_Max": "4",
      "Humidity_Min": "80.4",
      "Humidity_Max": "96",
      "Precip_Min": "0.037",
      "Precip_Max": "21.711",
      "PrecipProb_Min": "100",
      "PrecipProb_Max": "100",
      "Pressure_Min": "984.8",
      "Pressure_Max": "1021.1",
      "UVIndex_Min": "0",
      "UVIndex_Max": " 4",
      "Visibility_Min": " 5.9",
      "Visibility_Max": "15.7",
      "WindSpeed_Min": "9.9",
      "WindSpeed_Max": "34.5",
      "WindDirection_Min": "0.1",
      "WindDirection_Max": "191.7",
      "Sunrise_Max": " 07:38:06",
      "Sunrise_Min": "07:57:39",
      "Sunset_Max": "16:17:38",
      "Sunset_Min": "16:27:29",
      "Moonrise_Max": "00:55:58",
      "Moonrise_Min": "20:23:08",
      "Moonset_Max": "00:33:42",
      "Moonset_Min": "23:19:02"
    },
    {
      "Condition": "Cloudy",
      "Temperature_Min": " -4.2",
      "Temperature_Max": " 12.4",
      "Dew_Min": "-3",
      "Dew_Max": "8.4",
      "Feelslike_Min": "-5.1",
      "Feelslike_Max": "9.8",
      "Snow_Min": "0",
      "Snow_Max": "4",
      "Humidity_Min": "80.4",
      "Humidity_Max": "96",
      "Precip_Min": "0.1",
      "Precip_Max": "21.711",
      "PrecipProb_Min": "0",
      "PrecipProb_Max": "100",
      "Pressure_Min": "984.8",
      "Pressure_Max": "1024.1",
      "UVIndex_Min": "0",
      "UVIndex_Max": " 4",
      "Visibility_Min": " 5.9",
      "Visibility_Max": "15.7",
      "WindSpeed_Min": "6.3",
      "WindSpeed_Max": "34.5",
      "WindDirection_Min": "0.1",
      "WindDirection_Max": "359.9",
      "Sunrise_Max": " 07:38:06",
      "Sunrise_Min": "07:57:39",
      "Sunset_Max": "16:17:38",
      "Sunset_Min": "16:27:29",
      "Moonrise_Max": "00:55:58",
      "Moonrise_Min": "20:23:08",
      "Moonset_Max": "00:33:42",
      "Moonset_Min": "22:00:24"
    },
    {
      "Condition": "Freezing Rain",
      "Temperature_Min": " -4.2",
      "Temperature_Max": " 4.4",
      "Dew_Min": "-3",
      "Dew_Max": "1.1",
      "Feelslike_Min": "-5.1",
      "Feelslike_Max": "-0.6",
      "Snow_Min": "0",
      "Snow_Max": "1.5",
      "Humidity_Min": "86.6",
      "Humidity_Max": "96",
      "Precip_Min": "0.712",
      "Precip_Max": "4.519",
      "PrecipProb_Min": "100",
      "PrecipProb_Max": "100",
      "Pressure_Min": "1017.6",
      "Pressure_Max": "1018.9",
      "UVIndex_Min": "0",
      "UVIndex_Max": " 1",
      "Visibility_Min": " 5.9",
      "Visibility_Max": "9.7",
      "WindSpeed_Min": "14.7",
      "WindSpeed_Max": "18.2",
      "WindDirection_Min": "145.7",
      "WindDirection_Max": "150.7",
      "Sunrise_Max": " 07:52:32",
      "Sunrise_Min": "07:55:50",
      "Sunset_Max": "16:18:39",
      "Sunset_Min": "16:21:22",
      "Moonrise_Max": "00:55:58",
      "Moonrise_Min": "08:45:39",
      "Moonset_Max": "13:02:53",
      "Moonset_Min": "16:26:45"
    }
  ]
}